exchanger/__init__.py
exchanger-0.1.1b0.dist-info/METADATA
exchanger-0.1.1b0.dist-info/WHEEL
exchanger-0.1.1b0.dist-info/RECORD
